solid_dmft/__init__.py
solid_dmft/csc_flow.py
solid_dmft/dmft_cycle.py
solid_dmft/main.py
solid_dmft/version.py
solid_dmft/dft_managers/__init__.py
solid_dmft/dft_managers/mpi_helpers.py
solid_dmft/dft_managers/qe_manager.py
solid_dmft/dft_managers/vasp_manager.py
solid_dmft/dmft_tools/__init__.py
solid_dmft/dmft_tools/afm_mapping.py
solid_dmft/dmft_tools/convergence.py
solid_dmft/dmft_tools/formatter.py
solid_dmft/dmft_tools/greens_functions_mixer.py
solid_dmft/dmft_tools/initial_self_energies.py
solid_dmft/dmft_tools/interaction_hamiltonian.py
solid_dmft/dmft_tools/legendre_filter.py
solid_dmft/dmft_tools/manipulate_chemical_potential.py
solid_dmft/dmft_tools/matheval.py
solid_dmft/dmft_tools/observables.py
solid_dmft/dmft_tools/results_to_archive.py
solid_dmft/dmft_tools/solver.py
solid_dmft/gw_embedding/__init__.py
solid_dmft/gw_embedding/bdft_converter.py
solid_dmft/gw_embedding/gw_flow.py
solid_dmft/gw_embedding/iaft.py
solid_dmft/gw_embedding/qp_evs_to_eig.py
solid_dmft/io_tools/__init__.py
solid_dmft/io_tools/default.toml
solid_dmft/io_tools/dict_to_h5.py
solid_dmft/io_tools/postproc_toml_dict.py
solid_dmft/io_tools/verify_input_params.py
solid_dmft/postprocessing/__init__.py
solid_dmft/postprocessing/eval_U_cRPA_RESPACK.py
solid_dmft/postprocessing/eval_U_cRPA_Vasp.py
solid_dmft/postprocessing/maxent_gf_imp.py
solid_dmft/postprocessing/maxent_gf_latt.py
solid_dmft/postprocessing/maxent_sigma.py
solid_dmft/postprocessing/pade_sigma.py
solid_dmft/postprocessing/plot_correlated_bands.py
solid_dmft/util/__init__.py
solid_dmft/util/symmetrize_gamma_file.py
solid_dmft/util/write_kslice_to_h5.py
solid_dmft-3.3.3.dist-info/licenses/COPYING.txt
solid_dmft-3.3.3.dist-info/licenses/LICENSE.txt
solid_dmft-3.3.3.dist-info/METADATA
solid_dmft-3.3.3.dist-info/WHEEL
solid_dmft-3.3.3.dist-info/entry_points.txt
solid_dmft-3.3.3.dist-info/top_level.txt
solid_dmft-3.3.3.dist-info/RECORD
