Metadata-Version: 2.4
Name: solid_dmft
Version: 3.3.3
Summary: solid_dmft: a versatile python wrapper to perform DFT+DMFT calculations utilizing the TRIQS software library
Author-email: Alexander Hampel <mail@alexander-hampel.de>
Project-URL: Homepage, https://triqs.github.io/solid_dmft
Project-URL: Bug Tracker, https://github.com/triqs/solid_dmft/issues
Project-URL: Paper, https://doi.org/10.21105/joss.04623
Keywords: DMFT,DFT,triqs
Classifier: Programming Language :: Python :: 3
Classifier: License :: OSI Approved :: GNU General Public License v3 (GPLv3)
Classifier: Operating System :: OS Independent
Requires-Python: >=3.7
License-File: LICENSE.txt
License-File: COPYING.txt
Requires-Dist: numpy
Requires-Dist: scipy
Requires-Dist: scikit-image
Dynamic: license-file
